calfreeslots/__init__.py
calfreeslots-1.0.1.dist-info/entry_points.txt
calfreeslots-1.0.1.dist-info/WHEEL
calfreeslots-1.0.1.dist-info/METADATA
calfreeslots-1.0.1.dist-info/RECORD
