Metadata-Version: 2.1
Name: calfreeslots
Version: 1.0.1
Summary: Command line utility to print free calendar slots in the coming days.
License: MIT
Author: Johannes Köster
Author-email: johannes.koester@uni-due.de
Requires-Python: >=3.9,<4.0
Classifier: License :: OSI Approved :: MIT License
Classifier: Programming Language :: Python :: 3
Requires-Dist: arrow (>=1.2.3,<2.0.0)
Requires-Dist: icalendar (>=4.1.0,<5.0.0)
Requires-Dist: recurring-ical-events (>=1.0.2-beta.0,<2.0.0)
Requires-Dist: requests (>=2.28.1,<3.0.0)
